spacepass/__init__.py
spacepass/config.py
spacepass/run.py
spacepass/gui/__init__.py
spacepass/gui/dir_window.py
spacepass/parser/__init__.py
spacepass/parser/node.py
spacepass/parser/pass_dir.py
spacepass/parser/pass_file.py
spacepass/parser/pass_root.py
spacepass-0.4.dist-info/LICENSE
spacepass-0.4.dist-info/METADATA
spacepass-0.4.dist-info/WHEEL
spacepass-0.4.dist-info/entry_points.txt
spacepass-0.4.dist-info/top_level.txt
spacepass-0.4.dist-info/RECORD
