Metadata-Version: 2.1
Name: spacepass
Version: 0.4
Summary: A spacemacs inspired menu for pass password store
Home-page: https://github.com/pm-coelho/spacepass
Author: pmcoelho
Author-email: pmcoelho@protonmail.com
License: GPLv3+
Platform: UNKNOWN
Classifier: Development Status :: 3 - Alpha
Classifier: Environment :: X11 Applications
Classifier: Environment :: X11 Applications :: GTK
Classifier: Intended Audience :: End Users/Desktop
Classifier: License :: OSI Approved :: GNU General Public License v3 or later (GPLv3+)
Classifier: Operating System :: POSIX :: Linux
Classifier: Topic :: Security
Requires-Dist: spacemenu
Requires-Dist: ConfigArgParse
